rethread/__init__.py
rethread/rethread.py
rethread-1.0.1.dist-info/METADATA
rethread-1.0.1.dist-info/WHEEL
rethread-1.0.1.dist-info/top_level.txt
rethread-1.0.1.dist-info/RECORD
