Metadata-Version: 2.1
Name: rethread
Version: 1.0.1
Summary: Library for easy multithreading.
Author: ZeroIntensity
Author-email: <zintensitydev@gmail.com>
Maintainer: ZeroIntensity
License: MIT
Platform: UNKNOWN
Requires-Dist: typing-extensions
